catz/__init__.py
catz/app.py
catz/languages.py
catz/options.py
catz/styles.py
catz-0.9.0.dist-info/entry_points.txt
catz-0.9.0.dist-info/LICENSE
catz-0.9.0.dist-info/WHEEL
catz-0.9.0.dist-info/METADATA
catz-0.9.0.dist-info/RECORD
